<?xml version="1.0" encoding="UTF-8"?>
<export version="D">
  <design>
    <source>E:/PROJECT WORKING/18. KICARD/LED MAU MATOME/PCB_LED_MAU_MATOME.sch</source>
    <date>2018/01/23 02:07:14</date>
    <tool>Eeschema 4.0.7</tool>
    <sheet number="1" name="/" tstamps="/">
      <title_block>
        <title/>
        <company/>
        <rev/>
        <date/>
        <source>PCB_LED_MAU_MATOME.sch</source>
        <comment number="1" value=""/>
        <comment number="2" value=""/>
        <comment number="3" value=""/>
        <comment number="4" value=""/>
      </title_block>
    </sheet>
  </design>
  <components>
    <comp ref="J1">
      <value>Conn_01x06</value>
      <footprint>Connectors_JST:JST_XH_B06B-XH-A_06x2.50mm_Straight</footprint>
      <libsource lib="conn" part="Conn_01x06"/>
      <sheetpath names="/" tstamps="/"/>
      <tstamp>5A66C7DD</tstamp>
    </comp>
    <comp ref="D4">
      <value>LED</value>
      <footprint>LEDs:LED_D5.0mm</footprint>
      <libsource lib="device" part="LED"/>
      <sheetpath names="/" tstamps="/"/>
      <tstamp>5A66C875</tstamp>
    </comp>
    <comp ref="D3">
      <value>LED</value>
      <footprint>LEDs:LED_D5.0mm</footprint>
      <libsource lib="device" part="LED"/>
      <sheetpath names="/" tstamps="/"/>
      <tstamp>5A66C90B</tstamp>
    </comp>
    <comp ref="D2">
      <value>LED</value>
      <footprint>LEDs:LED_D5.0mm</footprint>
      <libsource lib="device" part="LED"/>
      <sheetpath names="/" tstamps="/"/>
      <tstamp>5A66C964</tstamp>
    </comp>
    <comp ref="D1">
      <value>LED</value>
      <footprint>LEDs:LED_D5.0mm</footprint>
      <libsource lib="device" part="LED"/>
      <sheetpath names="/" tstamps="/"/>
      <tstamp>5A66C96A</tstamp>
    </comp>
  </components>
  <libparts>
    <libpart lib="conn" part="Conn_01x06">
      <description>Generic connector, single row, 01x06</description>
      <docs>~</docs>
      <footprints>
        <fp>Connector*:*_??x*mm*</fp>
        <fp>Connector*:*1x??x*mm*</fp>
        <fp>Pin?Header?Straight?1X*</fp>
        <fp>Pin?Header?Angled?1X*</fp>
        <fp>Socket?Strip?Straight?1X*</fp>
        <fp>Socket?Strip?Angled?1X*</fp>
      </footprints>
      <fields>
        <field name="Reference">J</field>
        <field name="Value">Conn_01x06</field>
      </fields>
      <pins>
        <pin num="1" name="Pin_1" type="passive"/>
        <pin num="2" name="Pin_2" type="passive"/>
        <pin num="3" name="Pin_3" type="passive"/>
        <pin num="4" name="Pin_4" type="passive"/>
        <pin num="5" name="Pin_5" type="passive"/>
        <pin num="6" name="Pin_6" type="passive"/>
      </pins>
    </libpart>
    <libpart lib="device" part="LED">
      <description>LED generic</description>
      <footprints>
        <fp>LED*</fp>
      </footprints>
      <fields>
        <field name="Reference">D</field>
        <field name="Value">LED</field>
      </fields>
      <pins>
        <pin num="1" name="K" type="passive"/>
        <pin num="2" name="A" type="passive"/>
      </pins>
    </libpart>
  </libparts>
  <libraries>
    <library logical="device">
      <uri>C:\Program Files\KiCad\share\kicad\library\device.lib</uri>
    </library>
    <library logical="conn">
      <uri>C:\Program Files\KiCad\share\kicad\library\conn.lib</uri>
    </library>
  </libraries>
  <nets>
    <net code="1" name="Net-(D2-Pad1)">
      <node ref="D2" pin="1"/>
      <node ref="J1" pin="5"/>
    </net>
    <net code="2" name="Net-(D1-Pad1)">
      <node ref="D1" pin="1"/>
      <node ref="J1" pin="6"/>
    </net>
    <net code="3" name="Net-(D1-Pad2)">
      <node ref="D3" pin="2"/>
      <node ref="D1" pin="2"/>
      <node ref="D2" pin="2"/>
      <node ref="D4" pin="2"/>
      <node ref="J1" pin="2"/>
    </net>
    <net code="4" name="Net-(J1-Pad1)">
      <node ref="J1" pin="1"/>
    </net>
    <net code="5" name="Net-(D4-Pad1)">
      <node ref="D4" pin="1"/>
      <node ref="J1" pin="3"/>
    </net>
    <net code="6" name="Net-(D3-Pad1)">
      <node ref="D3" pin="1"/>
      <node ref="J1" pin="4"/>
    </net>
  </nets>
</export>
